{
  "posts": [
    {
      "id": 1,
      "title": "Post 1",
      "body": "Lorem ipsum dolor sit amet, consectetur adipiscing elit. Sed do eiusmod tempor incididunt ut labore et dolore magna aliqua.",
      "timestamp": 1770831475811
    },
    {
      "id": 2,
      "title": "Post 2",
      "body": "Ut enim ad minim veniam, quis nostrud exercitation ullamco laboris nisi ut aliquip ex ea commodo consequat.",
      "timestamp": 1770831475812
    },
    {
      "id": 3,
      "title": "Post 3",
      "body": "Duis aute irure dolor in reprehenderit in voluptate velit esse cillum dolore eu fugiat nulla pariatur.",
      "timestamp": 1770831475813
    }
  ],
  "users": [
    {
      "id": "4f4f9ce8-c27e-4ac0-bbab-d7f9c46e28f2",
      "name": "Margo",
      "email": "margo@gmail.com",
      "password": "$2a$10$RzNsqdIBouMipbAZzDxFPOf1Yy6MAG49IwV0uFZLRvMRbM0adqzGK",
      "createdAt": "2025-12-11T14:09:29.323Z"
    },
    {
      "id": "37d42238-a84d-47c4-8030-e3d0e91d43de",
      "name": "Alex",
      "email": "alex@gmail.com",
      "password": "$2b$10$9k6/VorxScyIjiJI5Y7hmO.ZYIzj5/2yji5/C74/GjdpKXw46zU5O",
      "createdAt": "2025-12-11T14:20:51.762Z"
    },
    {
      "id": "b408d67c-7784-4324-8d31-d36bc2a14e0e",
      "name": "John",
      "email": "john@gmail.com",
      "password": "$2b$10$n8sOO6mY6NmFjomlxVe3t.rzTskFMT2Nuv8h.Nvy8LxYxXrVXm4bW",
      "createdAt": "2025-12-11T14:21:06.694Z"
    },
    {
      "id": "2393735b-82c2-4ba4-a5c6-ae6b0ddc7eb6",
      "name": "Robert",
      "email": "robert@gmail.com",
      "password": "$2b$10$E0snNHnyXClyZ.4HkLbxFuJTzuUdAxa1833txHK5DHqZ4slPR0qcy",
      "createdAt": "2025-12-11T14:21:17.170Z"
    }
  ],
  "boards": [
    {
      "id": "d60275d0-b457-4531-85f9-8a98316b3433",
      "name": "Alex's board #1",
      "description": "Lorem ipsum dolor sit amet consectetur adipisicing elit. Porro, placeat!",
      "authorId": "37d42238-a84d-47c4-8030-e3d0e91d43de"
    },
    {
      "id": "b323afc7-9da4-43df-8ffb-732def134636",
      "name": "Alex's board #2 ",
      "description": "Lorem ipsum dolor, sit amet consectetur adipisicing elit. Tenetur illum eveniet quasi ex. Esse, tenetur id?",
      "authorId": "37d42238-a84d-47c4-8030-e3d0e91d43de"
    },
    {
      "id": "82535b97-7da7-438a-bcd8-670cc0eba828",
      "name": "John's board #1",
      "description": "Lorem ipsum dolor sit amet consectetur adipisicing elit. Recusandae dolorum repellendus, corrupti obcaecati nostrum dicta. Corrupti architecto officiis iusto assumenda?",
      "authorId": "b408d67c-7784-4324-8d31-d36bc2a14e0e"
    },
    {
      "id": "c0c827f4-05c6-4df0-893c-de3125089c2a",
      "name": "John's board #2",
      "description": "Lorem ipsum dolor sit amet consectetur adipisicing elit.",
      "authorId": "b408d67c-7784-4324-8d31-d36bc2a14e0e"
    },
    {
      "id": "e856ec00-7ecb-4456-9ca5-6bddf0a189ca",
      "name": "Robert's board #1",
      "description": "Lorem ipsum dolor sit amet consectetur adipisicing elit. Perspiciatis ipsa blanditiis quasi.",
      "authorId": "2393735b-82c2-4ba4-a5c6-ae6b0ddc7eb6"
    },
    {
      "id": "ca44aeed-0c2c-4bf0-b0d2-a4cb43e19bed",
      "name": "Robert's board #2",
      "description": "Lorem ipsum dolor sit, amet consectetur adipisicing elit. Voluptates molestiae aperiam natus maxime dignissimos.",
      "authorId": "2393735b-82c2-4ba4-a5c6-ae6b0ddc7eb6"
    }
  ],
  "tasks": [
    {
      "id": "4f32a8b9-1e7d-4c5f-9b2a-0d8c3f4e5a6b",
      "title": "Alex's task #1",
      "description": "Lorem ipsum dolor sit amet, consectetur adipiscing elit. Sed do eiusmod tempor incididunt ut labore et dolore magna aliqua. Ut enim ad minim veniam.",
      "workflow": "todo",
      "boardId": "d60275d0-b457-4531-85f9-8a98316b3433",
      "authorId": "37d42238-a84d-47c4-8030-e3d0e91d43de"
    },
    {
      "id": "5c1b9d0a-2f8e-4d6g-9c3b-1e9d4f5a6b7c",
      "title": "Alex's task #2",
      "description": "Duis aute irure dolor in reprehenderit in voluptate velit esse cillum dolore eu fugiat nulla pariatur. Excepteur sint occaecat cupidatat non proident.",
      "workflow": "progress",
      "boardId": "d60275d0-b457-4531-85f9-8a98316b3433",
      "authorId": "37d42238-a84d-47c4-8030-e3d0e91d43de"
    },
    {
      "id": "6d2c0e1b-3g9f-4e7h-9d4c-2f0e5a6b7c8d",
      "title": "Alex's task #3",
      "description": "Nemo enim ipsam voluptatem quia voluptas sit aspernatur aut odit aut fugit.",
      "workflow": "done",
      "boardId": "d60275d0-b457-4531-85f9-8a98316b3433",
      "authorId": "37d42238-a84d-47c4-8030-e3d0e91d43de"
    },
    {
      "id": "7e3d1f2c-4h0g-5f8i-9e5d-3g1f6b7c8d9e",
      "title": "Alex's task #4",
      "description": "Sed ut perspiciatis unde omnis iste natus error sit voluptatem accusantium doloremque laudantium, totam rem aperiam.",
      "workflow": "todo",
      "boardId": "d60275d0-b457-4531-85f9-8a98316b3433",
      "authorId": "37d42238-a84d-47c4-8030-e3d0e91d43de"
    },
    {
      "id": "8f4e2g3d-5i1h-6g9j-9f6e-4h2g7c8d9e0f",
      "title": "Alex's task #5",
      "description": "At vero eos et accusamus et iusto odio dignissimos ducimus qui blanditiis praesentium voluptatum deleniti atque corrupti quos dolores et quas molestias.",
      "workflow": "progress",
      "boardId": "d60275d0-b457-4531-85f9-8a98316b3433",
      "authorId": "37d42238-a84d-47c4-8030-e3d0e91d43de"
    },
    {
      "id": "9a5f3h4e-6j2i-7h0k-9g7f-5i3h8d9e0f1g",
      "title": "Alex's task #6",
      "description": "Similique sunt in culpa qui officia deserunt mollitia animi, id est laborum et dolorum fuga.",
      "workflow": "todo",
      "boardId": "d60275d0-b457-4531-85f9-8a98316b3433",
      "authorId": "37d42238-a84d-47c4-8030-e3d0e91d43de"
    },
    {
      "id": "a06g4i5f-7k3j-8i1l-9h8g-6j4i9e0f1g2h",
      "title": "Alex's task #7",
      "description": "Et harum quidem rerum facilis est et expedita distinctio.",
      "workflow": "done",
      "boardId": "d60275d0-b457-4531-85f9-8a98316b3433",
      "authorId": "37d42238-a84d-47c4-8030-e3d0e91d43de"
    },
    {
      "id": "b17h5j6g-8l4k-9j2m-9i9h-7k5j0f1g2h3i",
      "title": "Alex's task #8",
      "description": "Nam libero tempore, cum soluta nobis est eligendi optio cumque nihil impedit quo minus id quod maxime placeat facere possimus.",
      "workflow": "progress",
      "boardId": "d60275d0-b457-4531-85f9-8a98316b3433",
      "authorId": "37d42238-a84d-47c4-8030-e3d0e91d43de"
    },
    {
      "id": "c28i6k7h-9m5l-a03n-9j0i-8l6k1g2h3i4j",
      "title": "Alex's task #9",
      "description": "Omnis voluptas assumenda est, omnis dolor repellendus. Temporibus autem quibusdam et aut officiis.",
      "workflow": "todo",
      "boardId": "d60275d0-b457-4531-85f9-8a98316b3433",
      "authorId": "37d42238-a84d-47c4-8030-e3d0e91d43de"
    },
    {
      "id": "d39j7l8i-a06m-b14o-9k1j-9m7l2h3i4j5k",
      "title": "Alex's task #10",
      "description": "Itaque earum rerum hic tenetur a sapiente delectus, ut aut reiciendis voluptatibus maiores alias consequatur aut perferendis doloribus asperiores repellat.",
      "workflow": "done",
      "boardId": "d60275d0-b457-4531-85f9-8a98316b3433",
      "authorId": "37d42238-a84d-47c4-8030-e3d0e91d43de"
    },
    {
      "id": "e4a08m9j-b17n-c25p-a02k-a08m3i4j5k6l",
      "title": "Alex's task #11",
      "description": "Consectetur, adipisci velit, sed quia non numquam eius modi tempora incidunt ut labore et dolore magnam aliquam quaerat voluptatem.",
      "workflow": "todo",
      "boardId": "b323afc7-9da4-43df-8ffb-732def134636",
      "authorId": "37d42238-a84d-47c4-8030-e3d0e91d43de"
    },
    {
      "id": "f5b19n0k-c28o-d36q-b13l-b19n4j5k6l7m",
      "title": "Alex's task #12",
      "description": "Ut enim ad minima veniam, quis nostrum exercitationem ullam corporis suscipit laboriosam, nisi ut aliquid ex ea commodi consequatur?",
      "workflow": "progress",
      "boardId": "b323afc7-9da4-43df-8ffb-732def134636",
      "authorId": "37d42238-a84d-47c4-8030-e3d0e91d43de"
    },
    {
      "id": "g6c2a01l-d39p-e47r-c24m-c2a05k6l7m8n",
      "title": "Alex's task #13",
      "description": "Quis autem vel eum iure reprehenderit qui in ea voluptate velit esse quam nihil molestiae consequatur.",
      "workflow": "done",
      "boardId": "b323afc7-9da4-43df-8ffb-732def134636",
      "authorId": "37d42238-a84d-47c4-8030-e3d0e91d43de"
    },
    {
      "id": "h7d3b12m-e4a0-f58s-d35n-d3b16l7m8n9o",
      "title": "Alex's task #14",
      "description": "Vel illum qui dolorem eum fugiat quo voluptas nulla pariatur?",
      "workflow": "todo",
      "boardId": "b323afc7-9da4-43df-8ffb-732def134636",
      "authorId": "37d42238-a84d-47c4-8030-e3d0e91d43de"
    },
    {
      "id": "i8e4c23n-f5b1-g69t-e46o-e4c27m8n9o0p",
      "title": "Alex's task #15",
      "description": "Neque porro quisquam est, qui dolorem ipsum quia dolor sit amet, consectetur, adipisci velit.",
      "workflow": "progress",
      "boardId": "b323afc7-9da4-43df-8ffb-732def134636",
      "authorId": "37d42238-a84d-47c4-8030-e3d0e91d43de"
    },
    {
      "id": "j9f5d34o-g6c2-h70u-f57p-f5d38n9o0p1q",
      "title": "Alex's task #16",
      "description": "Minima veniam, quis nostrum exercitationem ullam corporis suscipit laboriosam, nisi ut aliquid ex ea commodi consequatur?",
      "workflow": "todo",
      "boardId": "b323afc7-9da4-43df-8ffb-732def134636",
      "authorId": "37d42238-a84d-47c4-8030-e3d0e91d43de"
    },
    {
      "id": "k0g6e45p-h7d3-i81v-g68q-g6e49o0p1q2r",
      "title": "Alex's task #17",
      "description": "Quis nostrum exercitationem ullam corporis suscipit laboriosam, nisi ut aliquid ex ea commodi consequatur?",
      "workflow": "done",
      "boardId": "b323afc7-9da4-43df-8ffb-732def134636",
      "authorId": "37d42238-a84d-47c4-8030-e3d0e91d43de"
    },
    {
      "id": "l1h7f56q-i8e4-j92w-h79r-h7f50p1q2r3s",
      "title": "John's task #1",
      "description": "Temporibus autem quibusdam et aut officiis debitis aut rerum necessitatibus saepe eveniet ut et voluptates repudiandae sint et molestiae non recusandae.",
      "workflow": "todo",
      "boardId": "82535b97-7da7-438a-bcd8-670cc0eba828",
      "authorId": "b408d67c-7784-4324-8d31-d36bc2a14e0e"
    },
    {
      "id": "m2i8g67r-j9f5-k03x-i80s-i8g61q2r3s4t",
      "title": "John's task #2",
      "description": "Itaque earum rerum hic tenetur a sapiente delectus, ut aut reiciendis voluptatibus maiores alias consequatur aut perferendis.",
      "workflow": "progress",
      "boardId": "82535b97-7da7-438a-bcd8-670cc0eba828",
      "authorId": "b408d67c-7784-4324-8d31-d36bc2a14e0e"
    },
    {
      "id": "n3j9h78s-k0g6-l14y-j91t-j9h72r3s4t5u",
      "title": "John's task #3",
      "description": "Doloribus asperiores repellat. Sed ut perspiciatis unde omnis iste natus error sit voluptatem accusantium doloremque laudantium.",
      "workflow": "done",
      "boardId": "82535b97-7da7-438a-bcd8-670cc0eba828",
      "authorId": "b408d67c-7784-4324-8d31-d36bc2a14e0e"
    },
    {
      "id": "o4k0i89t-l1h7-m25z-k02u-k0i83s4t5u6v",
      "title": "John's task #4",
      "description": "Totam rem aperiam, eaque ipsa quae ab illo inventore veritatis et quasi architecto beatae vitae dicta sunt explicabo.",
      "workflow": "todo",
      "boardId": "82535b97-7da7-438a-bcd8-670cc0eba828",
      "authorId": "b408d67c-7784-4324-8d31-d36bc2a14e0e"
    },
    {
      "id": "p5l1j90u-m2i8-n36a-l13v-l1j94t5u6v7w",
      "title": "John's task #5",
      "description": "Nemo enim ipsam voluptatem quia voluptas sit aspernatur aut odit aut fugit, sed quia consequuntur magni dolores eos qui ratione voluptatem sequi nesciunt.",
      "workflow": "progress",
      "boardId": "82535b97-7da7-438a-bcd8-670cc0eba828",
      "authorId": "b408d67c-7784-4324-8d31-d36bc2a14e0e"
    },
    {
      "id": "q6m2k01v-n3j9-o47b-m24w-m2k05u6v7w8x",
      "title": "John's task #6",
      "description": "Consequuntur magni dolores eos qui ratione voluptatem sequi nesciunt.",
      "workflow": "todo",
      "boardId": "82535b97-7da7-438a-bcd8-670cc0eba828",
      "authorId": "b408d67c-7784-4324-8d31-d36bc2a14e0e"
    },
    {
      "id": "r7n3l12w-o4k0-p58c-n35x-n3l16v7w8x9y",
      "title": "John's task #7",
      "description": "Neque porro quisquam est, qui dolorem ipsum quia dolor sit amet, consectetur, adipisci velit.",
      "workflow": "done",
      "boardId": "82535b97-7da7-438a-bcd8-670cc0eba828",
      "authorId": "b408d67c-7784-4324-8d31-d36bc2a14e0e"
    },
    {
      "id": "s8o4m23x-p5l1-q69d-o46y-o4m27w8x9y0z",
      "title": "John's task #8",
      "description": "Sunt in culpa qui officia deserunt mollitia animi, id est laborum et dolorum fuga.",
      "workflow": "todo",
      "boardId": "82535b97-7da7-438a-bcd8-670cc0eba828",
      "authorId": "b408d67c-7784-4324-8d31-d36bc2a14e0e"
    },
    {
      "id": "t9p5n34y-q6m2-r70e-p57z-p5n38x9y0z1a",
      "title": "John's task #9",
      "description": "Et expedita distinctio. Nam libero tempore, cum soluta nobis est eligendi optio cumque nihil impedit quo minus id quod maxime placeat facere.",
      "workflow": "progress",
      "boardId": "82535b97-7da7-438a-bcd8-670cc0eba828",
      "authorId": "b408d67c-7784-4324-8d31-d36bc2a14e0e"
    },
    {
      "id": "u0q6o45z-r7n3-s81f-q68a-q6o49y0z1a2b",
      "title": "John's task #10",
      "description": "Esse cillum dolore eu fugiat nulla pariatur. Excepteur sint occaecat cupidatat non proident, sunt in culpa qui officia deserunt mollit anim id est laborum.",
      "workflow": "progress",
      "boardId": "c0c827f4-05c6-4df0-893c-de3125089c2a",
      "authorId": "b408d67c-7784-4324-8d31-d36bc2a14e0e"
    },
    {
      "id": "v1r7p56a-s8o4-t92g-r79b-r7p50z1a2b3c",
      "title": "John's task #11",
      "description": "Ut enim ad minim veniam, quis nostrud exercitation ullamco laboris nisi ut aliquip ex ea commodo consequat.",
      "workflow": "todo",
      "boardId": "c0c827f4-05c6-4df0-893c-de3125089c2a",
      "authorId": "b408d67c-7784-4324-8d31-d36bc2a14e0e"
    },
    {
      "id": "w2s8q67b-t9p5-u03h-s80c-s8q61a2b3c4d",
      "title": "John's task #12",
      "description": "Duis aute irure dolor in reprehenderit in voluptate velit esse cillum dolore eu fugiat nulla pariatur.",
      "workflow": "done",
      "boardId": "c0c827f4-05c6-4df0-893c-de3125089c2a",
      "authorId": "b408d67c-7784-4324-8d31-d36bc2a14e0e"
    },
    {
      "id": "x3t9r78c-u0q6-v14i-t91d-t9r72b3c4d5e",
      "title": "John's task #13",
      "description": "Excepteur sint occaecat cupidatat non proident, sunt in culpa qui officia deserunt mollit anim id est laborum.",
      "workflow": "todo",
      "boardId": "c0c827f4-05c6-4df0-893c-de3125089c2a",
      "authorId": "b408d67c-7784-4324-8d31-d36bc2a14e0e"
    },
    {
      "id": "y4u0s89d-v1r7-w25j-u02e-u0s83c4d5e6f",
      "title": "John's task #14",
      "description": "Sed ut perspiciatis unde omnis iste natus error sit voluptatem accusantium doloremque laudantium, totam rem aperiam.",
      "workflow": "progress",
      "boardId": "c0c827f4-05c6-4df0-893c-de3125089c2a",
      "authorId": "b408d67c-7784-4324-8d31-d36bc2a14e0e"
    },
    {
      "id": "z5v1t90e-w2s8-x36k-v13f-v1t94d5e6f7g",
      "title": "John's task #15",
      "description": "Eaque ipsa quae ab illo inventore veritatis et quasi architecto beatae vitae dicta sunt explicabo. Nemo enim ipsam voluptatem.",
      "workflow": "done",
      "boardId": "c0c827f4-05c6-4df0-893c-de3125089c2a",
      "authorId": "b408d67c-7784-4324-8d31-d36bc2a14e0e"
    },
    {
      "id": "1a6w2u0f-x3t9-y47l-w24g-w2u05e6f7g8h",
      "title": "John's task #16",
      "description": "Voluptatem quia voluptas sit aspernatur aut odit aut fugit, sed quia consequuntur magni dolores eos qui ratione voluptatem sequi nesciunt.",
      "workflow": "todo",
      "boardId": "c0c827f4-05c6-4df0-893c-de3125089c2a",
      "authorId": "b408d67c-7784-4324-8d31-d36bc2a14e0e"
    },
    {
      "id": "2b7x3v1g-y4u0-z58m-x35h-x3v16f7g8h9i",
      "title": "John's task #17",
      "description": "Neque porro quisquam est, qui dolorem ipsum quia dolor sit amet.",
      "workflow": "progress",
      "boardId": "c0c827f4-05c6-4df0-893c-de3125089c2a",
      "authorId": "b408d67c-7784-4324-8d31-d36bc2a14e0e"
    },
    {
      "id": "3c8y4w2h-z5v1-1a9n-y46i-y4w27g8h9i0j",
      "title": "John's task #18",
      "description": "Adipisci velit, sed quia non numquam eius modi tempora incidunt ut labore et dolore magnam aliquam quaerat voluptatem.",
      "workflow": "done",
      "boardId": "c0c827f4-05c6-4df0-893c-de3125089c2a",
      "authorId": "b408d67c-7784-4324-8d31-d36bc2a14e0e"
    },
    {
      "id": "4d9z5x3i-1a6w-2b0o-z57j-z5x38h9i0j1k",
      "title": "Robert's task #1",
      "description": "Ut enim ad minima veniam, quis nostrum exercitationem ullam corporis suscipit laboriosam, nisi ut aliquid ex ea commodi consequatur? Quis autem vel eum.",
      "workflow": "todo",
      "boardId": "e856ec00-7ecb-4456-9ca5-6bddf0a189ca",
      "authorId": "2393735b-82c2-4ba4-a5c6-ae6b0ddc7eb6"
    },
    {
      "id": "5e0a6y4j-2b7x-3c1p-1a8k-1a6y9i0j1k2l",
      "title": "Robert's task #2",
      "description": "Iure reprehenderit qui in ea voluptate velit esse quam nihil molestiae consequatur, vel illum qui dolorem eum fugiat quo voluptas nulla pariatur.",
      "workflow": "progress",
      "boardId": "e856ec00-7ecb-4456-9ca5-6bddf0a189ca",
      "authorId": "2393735b-82c2-4ba4-a5c6-ae6b0ddc7eb6"
    },
    {
      "id": "6f1b7z5k-3c8y-4d2q-2b9l-2b7z0j1k2l3m",
      "title": "Robert's task #3",
      "description": "At vero eos et accusamus et iusto odio dignissimos ducimus qui blanditiis praesentium voluptatum deleniti atque corrupti quos dolores et quas molestias excepturi.",
      "workflow": "done",
      "boardId": "e856ec00-7ecb-4456-9ca5-6bddf0a189ca",
      "authorId": "2393735b-82c2-4ba4-a5c6-ae6b0ddc7eb6"
    },
    {
      "id": "7g2c8a6l-4d9z-5e3r-3c0m-3c8a1k2l3m4n",
      "title": "Robert's task #4",
      "description": "Sint occaecat cupidatat non proident, sunt in culpa qui officia deserunt mollitia animi, id est laborum et dolorum fuga.",
      "workflow": "todo",
      "boardId": "e856ec00-7ecb-4456-9ca5-6bddf0a189ca",
      "authorId": "2393735b-82c2-4ba4-a5c6-ae6b0ddc7eb6"
    },
    {
      "id": "8h3d9b7m-5e0a-6f4s-4d1n-4d9b2l3m4n5o",
      "title": "Robert's task #5",
      "description": "Et harum quidem rerum facilis est et expedita distinctio. Nam libero tempore, cum soluta nobis est eligendi optio.",
      "workflow": "progress",
      "boardId": "e856ec00-7ecb-4456-9ca5-6bddf0a189ca",
      "authorId": "2393735b-82c2-4ba4-a5c6-ae6b0ddc7eb6"
    },
    {
      "id": "9i4e0c8n-6f1b-7g5t-5e2o-5e0c3m4n5o6p",
      "title": "Robert's task #6",
      "description": "Nihil impedit quo minus id quod maxime placeat facere possimus, omnis voluptas assumenda est.",
      "workflow": "done",
      "boardId": "e856ec00-7ecb-4456-9ca5-6bddf0a189ca",
      "authorId": "2393735b-82c2-4ba4-a5c6-ae6b0ddc7eb6"
    },
    {
      "id": "a05f1d9o-7g2c-8h6u-6f3p-6f1d4n5o6p7q",
      "title": "Robert's task #7",
      "description": "Omnis dolor repellendus. Temporibus autem quibusdam et aut officiis debitis aut rerum necessitatibus.",
      "workflow": "todo",
      "boardId": "e856ec00-7ecb-4456-9ca5-6bddf0a189ca",
      "authorId": "2393735b-82c2-4ba4-a5c6-ae6b0ddc7eb6"
    },
    {
      "id": "b16g2e0p-8h3d-9i7v-7g4q-7g2e5o6p7q8r",
      "title": "Robert's task #8",
      "description": "Earum rerum hic tenetur a sapiente delectus, ut aut reiciendis voluptatibus maiores alias consequatur.",
      "workflow": "progress",
      "boardId": "e856ec00-7ecb-4456-9ca5-6bddf0a189ca",
      "authorId": "2393735b-82c2-4ba4-a5c6-ae6b0ddc7eb6"
    },
    {
      "id": "c27h3f1q-9i4e-a08w-8h5r-8h3f6p7q8r9s",
      "title": "Robert's task #9",
      "description": "Perferendis doloribus asperiores repellat. Lorem ipsum dolor sit amet, consectetur adipiscing elit.",
      "workflow": "done",
      "boardId": "e856ec00-7ecb-4456-9ca5-6bddf0a189ca",
      "authorId": "2393735b-82c2-4ba4-a5c6-ae6b0ddc7eb6"
    },
    {
      "id": "d38i4g2r-a05f-b19x-9i6s-9i4g7q8r9s0t",
      "title": "Robert's task #10",
      "description": "Sed do eiusmod tempor incididunt ut labore et dolore magna aliqua. Ut enim ad minim veniam, quis nostrud exercitation ullamco laboris nisi ut aliquip ex ea commodo.",
      "workflow": "todo",
      "boardId": "e856ec00-7ecb-4456-9ca5-6bddf0a189ca",
      "authorId": "2393735b-82c2-4ba4-a5c6-ae6b0ddc7eb6"
    },
    {
      "id": "e49j5h3s-b16g-c20y-a07t-a05h8r9s0t1u",
      "title": "Robert's task #11",
      "description": "Reprehenderit in voluptate velit esse cillum dolore eu fugiat nulla pariatur.",
      "workflow": "progress",
      "boardId": "e856ec00-7ecb-4456-9ca5-6bddf0a189ca",
      "authorId": "2393735b-82c2-4ba4-a5c6-ae6b0ddc7eb6"
    },
    {
      "id": "f5a06i4t-c27h-d31z-b18u-b16i9s0t1u2v",
      "title": "Robert's task #12",
      "description": "Duis aute irure dolor in reprehenderit in voluptate velit esse cillum dolore eu fugiat nulla pariatur. Excepteur sint occaecat cupidatat non proident.",
      "workflow": "done",
      "boardId": "ca44aeed-0c2c-4bf0-b0d2-a4cb43e19bed",
      "authorId": "2393735b-82c2-4ba4-a5c6-ae6b0ddc7eb6"
    },
    {
      "id": "g6b17j5u-d38i-e42a-c29v-c27j0t1u2v3w",
      "title": "Robert's task #13",
      "description": "Sed ut perspiciatis unde omnis iste natus error sit voluptatem accusantium doloremque laudantium.",
      "workflow": "todo",
      "boardId": "ca44aeed-0c2c-4bf0-b0d2-a4cb43e19bed",
      "authorId": "2393735b-82c2-4ba4-a5c6-ae6b0ddc7eb6"
    },
    {
      "id": "h7c28k6v-e49j-f53b-d30w-d38k1u2v3w4x",
      "title": "Robert's task #14",
      "description": "Totam rem aperiam, eaque ipsa quae ab illo inventore veritatis et quasi architecto beatae vitae dicta sunt explicabo.",
      "workflow": "progress",
      "boardId": "ca44aeed-0c2c-4bf0-b0d2-a4cb43e19bed",
      "authorId": "2393735b-82c2-4ba4-a5c6-ae6b0ddc7eb6"
    },
    {
      "id": "i8d39l7w-f5a0-g64c-e41x-e49l2v3w4x5y",
      "title": "Robert's task #15",
      "description": "Nemo enim ipsam voluptatem quia voluptas sit aspernatur aut odit aut fugit.",
      "workflow": "done",
      "boardId": "ca44aeed-0c2c-4bf0-b0d2-a4cb43e19bed",
      "authorId": "2393735b-82c2-4ba4-a5c6-ae6b0ddc7eb6"
    },
    {
      "id": "j9e4a08x-g6b1-h75d-f52y-f5a03w4x5y6z",
      "title": "Robert's task #16",
      "description": "At vero eos et accusamus et iusto odio dignissimos ducimus qui blanditiis praesentium voluptatum deleniti atque corrupti quos dolores et quas molestias.",
      "workflow": "todo",
      "boardId": "ca44aeed-0c2c-4bf0-b0d2-a4cb43e19bed",
      "authorId": "2393735b-82c2-4ba4-a5c6-ae6b0ddc7eb6"
    },
    {
      "id": "k0f5b19y-h7c2-i86e-g63z-g6b14x5y6z7a",
      "title": "Robert's task #17",
      "description": "Similique sunt in culpa qui officia deserunt mollitia animi, id est laborum et dolorum fuga.",
      "workflow": "progress",
      "boardId": "ca44aeed-0c2c-4bf0-b0d2-a4cb43e19bed",
      "authorId": "2393735b-82c2-4ba4-a5c6-ae6b0ddc7eb6"
    },
    {
      "id": "l1g6c20z-i8d3-j97f-h74a-h7c25y6z7a8b",
      "title": "Robert's task #18",
      "description": "Et harum quidem rerum facilis est et expedita distinctio. Nam libero tempore.",
      "workflow": "done",
      "boardId": "ca44aeed-0c2c-4bf0-b0d2-a4cb43e19bed",
      "authorId": "2393735b-82c2-4ba4-a5c6-ae6b0ddc7eb6"
    }
  ]
}